.coderabbit.yaml
.gitbook.yaml
CONTRIBUTING.md
README.md
mlstacks/VERSION
mlstacks/__init__.py
mlstacks/analytics/__init__.py
mlstacks/analytics/client.py
mlstacks/cli/__init__.py
mlstacks/cli/cli.py
mlstacks/constants.py
mlstacks/enums.py
mlstacks/models/__init__.py
mlstacks/models/component.py
mlstacks/models/stack.py
mlstacks/terraform/aws-modular/.gitignore
mlstacks/terraform/aws-modular/.terraformignore
mlstacks/terraform/aws-modular/README.md
mlstacks/terraform/aws-modular/aws_account.tf
mlstacks/terraform/aws-modular/cert_manager.tf
mlstacks/terraform/aws-modular/configure_docker.tf
mlstacks/terraform/aws-modular/configure_kubectl.tf
mlstacks/terraform/aws-modular/ecr.tf
mlstacks/terraform/aws-modular/eks.tf
mlstacks/terraform/aws-modular/get_cluster_info.sh
mlstacks/terraform/aws-modular/get_cluster_token.sh
mlstacks/terraform/aws-modular/helm.tf
mlstacks/terraform/aws-modular/istio.tf
mlstacks/terraform/aws-modular/kubeflow.tf
mlstacks/terraform/aws-modular/kubernetes.tf
mlstacks/terraform/aws-modular/locals.tf
mlstacks/terraform/aws-modular/metadata.yaml
mlstacks/terraform/aws-modular/mlflow.tf
mlstacks/terraform/aws-modular/nginx_ingress.tf
mlstacks/terraform/aws-modular/output_file.tf
mlstacks/terraform/aws-modular/outputs.tf
mlstacks/terraform/aws-modular/s3.tf
mlstacks/terraform/aws-modular/sagemaker.tf
mlstacks/terraform/aws-modular/seldon.tf
mlstacks/terraform/aws-modular/tekton.tf
mlstacks/terraform/aws-modular/terraform.tf
mlstacks/terraform/aws-modular/values.tfvars.json
mlstacks/terraform/aws-modular/variables.tf
mlstacks/terraform/aws-modular/vpc.tf
mlstacks/terraform/aws-modular/zenml.tf
mlstacks/terraform/aws-remote-state/main.tf
mlstacks/terraform/aws-remote-state/outputs.tf
mlstacks/terraform/aws-remote-state/variables.tf
mlstacks/terraform/gcp-modular/.gitignore
mlstacks/terraform/gcp-modular/.terraformignore
mlstacks/terraform/gcp-modular/README.md
mlstacks/terraform/gcp-modular/cert_manager.tf
mlstacks-0.10.0.dist-info/LICENSE
mlstacks-0.10.0.dist-info/METADATA
mlstacks-0.10.0.dist-info/WHEEL
mlstacks-0.10.0.dist-info/entry_points.txt
mlstacks-0.10.0.dist-info/RECORD
