Metadata-Version: 2.1
Name: mlstacks
Version: 0.10.0
Summary: MLStacks MLStacks.
Home-page: https://mlstacks.zenml.io
License: Apache-2.0
Keywords: machine learning,production,pipeline,mlops,devops
Author: ZenML GmbH
Author-email: info@zenml.io
Requires-Python: >=3.8,<3.13
Classifier: Development Status :: 3 - Alpha
Classifier: Intended Audience :: Developers
Classifier: Intended Audience :: Education
Classifier: Intended Audience :: Information Technology
Classifier: Intended Audience :: Science/Research
Classifier: Intended Audience :: System Administrators
Classifier: License :: OSI Approved :: Apache Software License
Classifier: Programming Language :: Python :: 3
Classifier: Programming Language :: Python :: 3.8
Classifier: Programming Language :: Python :: 3.9
Classifier: Programming Language :: Python :: 3.10
Classifier: Programming Language :: Python :: 3.11
Classifier: Programming Language :: Python :: 3.12
Classifier: Programming Language :: Python :: 3 :: Only
Classifier: Topic :: Scientific/Engineering :: Artificial Intelligence
Classifier: Topic :: Software Development :: Libraries :: Python Modules
Classifier: Topic :: System :: Distributed Computing
Classifier: Typing :: Typed
Provides-Extra: dev
Requires-Dist: analytics-python (>=1.4.0,<2.0.0)
Requires-Dist: click (>=8.0.1,<8.1.4)
Requires-Dist: darglint (>=1.8.1,<2.0.0) ; extra == "dev"
Requires-Dist: hypothesis (>=6.43.1,<7.0.0) ; extra == "dev"
Requires-Dist: mypy (>=1.7.1,<2.0.0) ; extra == "dev"
Requires-Dist: pydantic (>=2.8,<2.9)
Requires-Dist: pytest (>=7.4.0,<8.0.0) ; extra == "dev"
Requires-Dist: pytest-clarity (>=1.0.1,<2.0.0) ; extra == "dev"
Requires-Dist: pytest-cov (>=4.1.0,<5.0.0) ; extra == "dev"
Requires-Dist: pytest-randomly (>=3.10.1,<4.0.0) ; extra == "dev"
Requires-Dist: python-terraform (>=0.10.1,<0.11.0)
Requires-Dist: pyyaml (>=6.0.1)
Requires-Dist: rich (>=12.0.0,<13.0.0)
Requires-Dist: ruff (>=0.1.7) ; extra == "dev"
Requires-Dist: setuptools
Requires-Dist: types-PyYAML (>=6.0.0,<7.0.0) ; extra == "dev"
Requires-Dist: types-requests (>=2.30.0,<3.0.0) ; extra == "dev"
Requires-Dist: types-setuptools (>=57.4.2,<58.0.0) ; extra == "dev"
Project-URL: Documentation, https://mlstacks.zenml.io/
Project-URL: Repository, https://github.com/zenml-io/mlstacks
